TP1_ALU/TP1_ALU.srcs/sources_1/new/ALU_Core.v
`timescale 1ns / 1ps
//////////////////////////////////////////////////////////////////////////////////
// Company: UNC
// Module Name: ALU_Core
// Project Name: TP2-UART
// Description: Modulo puramente combinacional con las operaciones 
//              Aritmeticas y Logicas requeridas. 
//////////////////////////////////////////////////////////////////////////////////

module ALU_Core 
#(
    parameter NB_DATA = 8,
    parameter NB_OP   = 6 
)
(
    output wire [NB_DATA - 1 : 0] o_result,
    
    input wire [NB_DATA - 1 : 0] i_data_a, // dato A
    input wire [NB_DATA - 1 : 0] i_data_b, // dato B
    input wire [NB_OP   - 1 : 0] i_opcode  // Operacion
);
    
    localparam [NB_OP - 1 : 0] ADD = 6'b100000;
    localparam [NB_OP - 1 : 0] SUB = 6'b100010;
    localparam [NB_OP - 1 : 0] AND = 6'b100100;
    localparam [NB_OP - 1 : 0] OR  = 6'b100101;
    localparam [NB_OP - 1 : 0] XOR = 6'b100110;
    localparam [NB_OP - 1 : 0] SRA = 6'b000011;
    localparam [NB_OP - 1 : 0] SRL = 6'b000010;
    localparam [NB_OP - 1 : 0] NOR = 6'b100111;
  
    reg [NB_DATA - 1 : 0] res;
  
    always @(*)
    begin
        case(i_opcode)
            ADD : res = i_data_a + i_data_b;
            SUB : res = i_data_a - i_data_b;
            AND : res = i_data_a & i_data_b;
            OR  : res = i_data_a | i_data_b;
            XOR : res = i_data_a ^ i_data_b;
            SRA : res = $signed(i_data_a) >>> i_data_b;
            SRL : res = i_data_a >> i_data_b;
            NOR : res = ~(i_data_a | i_data_b);
            default : res = {NB_DATA{1'b0}};
        endcase
    end
  
    assign o_result = res;
  
endmodule

TP1_ALU/TP1_ALU.srcs/sources_1/new/Registros.v
`timescale 1ns / 1ps
//////////////////////////////////////////////////////////////////////////////////
// Company: UNC
// Engineer: 
// 
// Create Date: 08/27/2026 07:31:38 PM
// Design Name: 
// Module Name: Registros
// Project Name:TP1-ALU 
// Target Devices: 
// Tool Versions: 
// Description: 
// 
// Dependencies: 
// 
// Revision:
// Revision 0.01 - File Created
// Additional Comments:
// 
//////////////////////////////////////////////////////////////////////////////////


module Registros
#(
    parameter NB_DATA = 8,
    parameter NB_OP   = 6
)
(
    input  wire [NB_DATA - 1 : 0]      i_switches,  
    input  wire                        clk,          // Señal de clock para los registros
    input  wire                        i_load_1,     // Señal para cargar A
    input  wire                        i_load_2,     // Señal para cargar B
    input  wire                        i_load_3,     // Señal para cargar opcode y disparar resultado
    input  wire [NB_DATA - 1 : 0]      i_alu_result, // Resultado que sale de la ALU
    
    output reg [NB_DATA - 1 : 0]      o_reg_a,
    output reg [NB_DATA - 1 : 0]      o_reg_b,
    output reg [NB_OP - 1 : 0]        o_reg_opcode,
    output reg [NB_DATA - 1 : 0]      o_reg_result
    
);

    // Reg A
    always @(posedge clk)
    begin
        if(i_load_1 == 1)
            o_reg_a <= i_switches;
    end

    // Reg B
    always @(posedge clk)
    begin
        if(i_load_2 == 1)
            o_reg_b <= i_switches;
    end

    // Reg Opcode
    reg load_3_dly; // Señal load_3 retardada medio ciclo de clock
    
    always @(posedge clk)
    begin
        load_3_dly <= i_load_3;
        
        if(i_load_3 == 1)
            o_reg_opcode <= i_switches[NB_OP - 1 : 0];
    end
    
    // Reg Salida
    always @(posedge clk)
    begin
        if(load_3_dly == 1)
            o_reg_result <= i_alu_result;
    end
endmodule

TP1_ALU/TP1_ALU.srcs/sources_1/new/ALU_Top.v
`timescale 1ns / 1ps
//////////////////////////////////////////////////////////////////////////////////
// Company: UNC
// Engineer: 
// 
// Create Date: 08/27/2026 07:31:38 PM
// Design Name: 
// Module Name: ALU_Top
// Project Name:TP1-ALU 
// Target Devices: 
// Tool Versions: 
// Description: 
// 
// Dependencies: 
// 
// Revision:
// Revision 0.01 - File Created
// Additional Comments:
// 
//////////////////////////////////////////////////////////////////////////////////

module ALU_Top
#(
    parameter NB_DATA = 8,
    parameter NB_OP   = 6
)
(
    input  wire [NB_DATA - 1 : 0]      i_switches,  
    input  wire                        clk,          // Señal de clock para los registros
    input  wire                        i_load_1,     // Señal para cargar A
    input  wire                        i_load_2,     // Señal para cargar B
    input  wire                        i_load_3,     // Señal para cargar opcode y disparar resultado
    
    output wire [NB_DATA - 1 : 0]      o_leds
);
    wire [NB_DATA - 1 : 0] alu_result;
    wire [NB_DATA - 1 : 0] reg_result;
    wire [NB_DATA - 1 : 0] reg_a;
    wire [NB_DATA - 1 : 0] reg_b;
    wire [NB_OP - 1 : 0]   reg_opcode;
    
    // Instancia del modulo Registros
    Registros #(
        .NB_DATA (NB_DATA),
        .NB_OP   (NB_OP)
    ) registros_inst(
        .i_switches     (i_switches),
        .clk            (clk),
        .i_load_1       (i_load_1),    
        .i_load_2       (i_load_2),     
        .i_load_3       (i_load_3),     
        .i_alu_result   (alu_result),
    
        .o_reg_a        (reg_a),
        .o_reg_b        (reg_b),
        .o_reg_opcode   (reg_opcode),
        .o_reg_result   (reg_result)
    );

    // Instancia del modulo ALU_Core
    ALU_Core #(
        .NB_DATA (NB_DATA),
        .NB_OP   (NB_OP)
    ) alu_core_inst (
        .o_result  (alu_result),
        
        .i_data_a  (reg_a),
        .i_data_b  (reg_b),
        .i_opcode  (reg_opcode)
    );

    assign o_leds = reg_result;

endmodule

TP1_ALU/TP1_ALU.srcs/sim_1/new/test_ALU_Top.v
`timescale 1ns / 1ps
//////////////////////////////////////////////////////////////////////////////////
// Company: UNC
// Engineer: 
// 
// Create Date: 08/27/2026 07:41:13 PM
// Design Name: 
// Module Name: test_ALU_Top
// Project Name: TP1_ALU
// Target Devices: 
// Tool Versions: 
// Description: 
// 
// Dependencies: 
// 
// Revision:
// Revision 0.01 - File Created
// Additional Comments:
// 
//////////////////////////////////////////////////////////////////////////////////

module test_ALU_Top;
    parameter NB_DATA = 8;
    parameter NB_OP   = 6;
    parameter CLK_PERIOD = 10;

    // Entradas / Salidas
    reg  [NB_DATA - 1 : 0] i_switches;
    reg                    clk;
    reg                    i_load_1;
    reg                    i_load_2;
    reg                    i_load_3;
    wire [NB_DATA - 1 : 0] o_leds;

    // Instancia del DUT
    ALU_Top #(
        .NB_DATA (NB_DATA),
        .NB_OP   (NB_OP)
    ) DUT (
        .i_switches (i_switches),
        .clk        (clk),
        .i_load_1   (i_load_1),
        .i_load_2   (i_load_2),
        .i_load_3   (i_load_3),
        .o_leds     (o_leds)
    );

    // ---------- Generación de clock ----------
    initial clk = 0;
    always #(CLK_PERIOD/2) clk = ~clk;

    // Funciones reutilizables
    task load_a(input [NB_DATA - 1 : 0] value);
    begin
        i_switches = value;
        i_load_1   = 1;
        #(CLK_PERIOD);          // un flanco de clock -> reg_a se carga
        i_load_1   = 0;
        #(CLK_PERIOD);
    end
    endtask

    task load_b(input [NB_DATA - 1 : 0] value);
    begin
        i_switches = value;
        i_load_2   = 1;
        #(CLK_PERIOD);          // un flanco de clock -> reg_b se carga
        i_load_2   = 0;
        #(CLK_PERIOD);
    end
    endtask

    task load_opcode(input [NB_OP - 1 : 0] value);
    begin
        i_switches = value;
        i_load_3   = 1;
        #(CLK_PERIOD);          // un flanco de clock -> reg_opcode se carga
        i_load_3   = 0;
        #(CLK_PERIOD);
    end
    endtask

    // ---------- Estímulos ----------
    initial begin
        $dumpfile("dump.vcd");
        $dumpvars(0, test_ALU_Top);

        i_switches = 0;
        i_load_1   = 0;
        i_load_2   = 0;
        i_load_3   = 0;
        #(CLK_PERIOD*2);

        // Caso 1: ADD, 5 + 3 = 8
        load_a(8'd5);
        load_b(8'd3);
        load_opcode(6'b100000);
        #10 $display("Caso 1  (ADD 5+3)        o_leds=%d  (esperado 8)", o_leds);

        // Caso 2: SUB, 10 - 4 = 6
        load_a(8'd10);
        load_b(8'd4);
        load_opcode(6'b100010);
        #10 $display("Caso 2  (SUB 10-4)       o_leds=%d  (esperado 6)", o_leds);

        // Caso 3: AND, 0xCC & 0xAA = 0x88
        load_a(8'hCC);
        load_b(8'hAA);
        load_opcode(6'b100100);
        #10 $display("Caso 3  (AND CC&AA)      o_leds=%h  (esperado 88)", o_leds);

        // Caso 4: OR, 0xCC | 0xAA = 0xEE
        load_a(8'hCC);
        load_b(8'hAA);
        load_opcode(6'b100101);
        #10 $display("Caso 4  (OR  CC|AA)      o_leds=%h  (esperado EE)", o_leds);

        // Caso 5: XOR, 0xCC ^ 0xAA = 0x66
        load_a(8'hCC);
        load_b(8'hAA);
        load_opcode(6'b100110);
        #10 $display("Caso 5  (XOR CC^AA)      o_leds=%h  (esperado 66)", o_leds);

        // Caso 6: SRL, 0x80 >> 2 = 0x20 (shift logico, rellena con 0)
        load_a(8'h80);
        load_b(8'd2);
        load_opcode(6'b000010);
        #10 $display("Caso 6  (SRL 80>>2)      o_leds=%h  (esperado 20)", o_leds);

        // Caso 7: SRA, 0x80 >>> 5 -> 8
        load_a(8'h80);
        load_b(8'd5);
        load_opcode(6'b000011);
        #10 $display("Caso 7  (SRA 80>>>5)     o_leds=%h (esperado FC)", o_leds);

        // Caso 8: NOR, 0x0F ~| 0xF0 = 0x00
        load_a(8'h0F);
        load_b(8'hF0);
        load_opcode(6'b100111);
        #10 $display("Caso 8  (NOR 0F,F0)      o_leds=%h  (esperado 00)", o_leds);

        // Caso 9: ADD con overflow, 200 + 100 = 300 -> 1 bit de Carry + 8 bits de salida (44d)
        load_a(8'd200);
        load_b(8'd100);
        load_opcode(6'b100000);
        #10 $display("Caso 9  (ADD overflow)   o_leds=%d  (esperado 44, 300 mod 256)", o_leds);

        // Caso 10: shift por 0 (no deberia cambiar nada)
        load_a(8'hA5);
        load_b(8'd0);
        load_opcode(6'b000010);   // SRL
        #10 $display("Caso 10 (SRL shift 0)    o_leds=%h  (esperado A5, sin cambios)", o_leds);

        // Caso 11: shift por un valor mayor al ancho de datos (8 bits)
        load_a(8'hFF);
        load_b(8'd10);            // desplazar 10 posiciones en un dato de 8 bits
        load_opcode(6'b000010);   // SRL
        #10 $display("Caso 11 (SRL shift >8)   o_leds=%h  (esperado 00, se vacia el registro)", o_leds);
        
        // Caso 12: cambiar solo el reg A0
        // no deberia cambiar la salida al no haber precionado el boton 3
        load_a(8'd20);
        #10 $display("Caso 12 (solo A cambio)  o_leds=%d  (esperado 0 TODAVIA, no se aprieto boton 3)", o_leds);

        // Caso 13: ahora si apretamos boton 3 de nuevo, sin cambiar opcode,
        // deberia recalcular con el A nuevo (20) y el B viejo (10) -> 30
        load_opcode(6'b100000); // ADD
        #10 $display("Caso 13 (dispara con A nuevo) o_leds=%d  (esperado 30)", o_leds);

        #(CLK_PERIOD*4);
        $finish;
    end

endmodule

TP1_ALU/TP1_ALU.sim/sim_1/behav/xsim/dump.vcd
$date
   Fri Sep  4 12:41:51 2026
$end

$version
  2026.1
  $dumpfile ("dump.vcd") 
$end

$timescale
  1ps
$end

$scope module test_ALU_Top $end
$var reg 8 ! i_switches [7:0] $end
$var reg 1 " clk $end
$var reg 1 # i_load_1 $end
$var reg 1 $ i_load_2 $end
$var reg 1 % i_load_3 $end
$var wire 8 & o_leds [7:0] $end
$scope module DUT $end
$var wire 8 ' i_switches [7:0] $end
$var wire 1 ( clk $end
$var wire 1 ) i_load_1 $end
$var wire 1 * i_load_2 $end
$var wire 1 + i_load_3 $end
$var wire 8 & o_leds [7:0] $end
$var wire 8 , alu_result [7:0] $end
$var wire 8 - reg_result [7:0] $end
$var wire 8 . reg_a [7:0] $end
$var wire 8 / reg_b [7:0] $end
$var wire 6 0 reg_opcode [5:0] $end
$scope module registros_inst $end
$var wire 8 ' i_switches [7:0] $end
$var wire 1 ( clk $end
$var wire 1 ) i_load_1 $end
$var wire 1 * i_load_2 $end
$var wire 1 + i_load_3 $end
$var wire 8 , i_alu_result [7:0] $end
$var reg 8 1 o_reg_a [7:0] $end
$var reg 8 2 o_reg_b [7:0] $end
$var reg 6 3 o_reg_opcode [5:0] $end
$var reg 8 4 o_reg_result [7:0] $end
$var reg 1 5 load_3_dly $end
$upscope $end
$scope module alu_core_inst $end
$var wire 8 , o_result [7:0] $end
$var wire 8 . i_data_a [7:0] $end
$var wire 8 / i_data_b [7:0] $end
$var wire 6 0 i_opcode [5:0] $end
$var reg 8 6 res [7:0] $end
$upscope $end
$upscope $end
$scope task load_a $end
$var reg 8 7 value [7:0] $end
$upscope $end
$scope task load_b $end
$var reg 8 8 value [7:0] $end
$upscope $end
$scope task load_opcode $end
$var reg 6 9 value [5:0] $end
$upscope $end
$upscope $end
$enddefinitions $end

#0
$dumpvars
b0 !
0"
0#
0$
0%
bx &
b0 '
0(
0)
0*
0+
bx ,
bx -
bx .
bx /
bx 0
bx 1
bx 2
bx 3
bx 4
x5
bx 6
bx 7
bx 8
bx 9
$end

#5000
1"
1(
05

#10000
0"
0(

#15000
1"
1(

#20000
b101 !
0"
1#
b101 '
0(
1)
b101 7

#25000
1"
1(
b0 ,
b101 .
b101 1
b0 6

#30000
0"
0#
0(
0)

#35000
1"
1(

#40000
b11 !
0"
1$
b11 '
0(
1*
b11 8

#45000
1"
1(
b11 /
b11 2

#50000
0"
0$
0(
0*

#55000
1"
1(

#60000
b100000 !
0"
1%
b100000 '
0(
1+
b100000 9

#65000
1"
1(
b1000 ,
b100000 0
b100000 3
15
b1000 6

#70000
0"
0%
0(
0+

#75000
1"
b1000 &
1(
b1000 -
b1000 4
05

#80000
0"
0(

#85000
1"
1(

#90000
b1010 !
0"
1#
b1010 '
0(
1)
b1010 7

#95000
1"
1(
b1101 ,
b1010 .
b1010 1
b1101 6

#100000
0"
0#
0(
0)

#105000
1"
1(

#110000
b100 !
0"
1$
b100 '
0(
1*
b100 8

#115000
1"
1(
b1110 ,
b100 /
b100 2
b1110 6

#120000
0"
0$
0(
0*

#125000
1"
1(

#130000
b100010 !
0"
1%
b100010 '
0(
1+
b100010 9

#135000
1"
1(
b110 ,
b100010 0
b100010 3
15
b110 6

#140000
0"
0%
0(
0+

#145000
1"
b110 &
1(
b110 -
b110 4
05

#150000
0"
0(

#155000
1"
1(

#160000
b11001100 !
0"
1#
b11001100 '
0(
1)
b11001100 7

#165000
1"
1(
b11001000 ,
b11001100 .
b11001100 1
b11001000 6

#170000
0"
0#
0(
0)

#175000
1"
1(

#180000
b10101010 !
0"
1$
b10101010 '
0(
1*
b10101010 8

#185000
1"
1(
b100010 ,
b10101010 /
b10101010 2
b100010 6

#190000
0"
0$
0(
0*

#195000
1"
1(

#200000
b100100 !
0"
1%
b100100 '
0(
1+
b100100 9

#205000
1"
1(
b10001000 ,
b100100 0
b100100 3
15
b10001000 6

#210000
0"
0%
0(
0+

#215000
1"
b10001000 &
1(
b10001000 -
b10001000 4
05

#220000
0"
0(

#225000
1"
1(

#230000
b11001100 !
0"
1#
b11001100 '
0(
1)

#235000
1"
1(

#240000
0"
0#
0(
0)

#245000
1"
1(

#250000
b10101010 !
0"
1$
b10101010 '
0(
1*

#255000
1"
1(

#260000
0"
0$
0(
0*

#265000
1"
1(

#270000
b100101 !
0"
1%
b100101 '
0(
1+
b100101 9

#275000
1"
1(
b11101110 ,
b100101 0
b100101 3
15
b11101110 6

#280000
0"
0%
0(
0+

#285000
1"
b11101110 &
1(
b11101110 -
b11101110 4
05

#290000
0"
0(

#295000
1"
1(

#300000
b11001100 !
0"
1#
b11001100 '
0(
1)

#305000
1"
1(

#310000
0"
0#
0(
0)

#315000
1"
1(

#320000
b10101010 !
0"
1$
b10101010 '
0(
1*

#325000
1"
1(

#330000
0"
0$
0(
0*

#335000
1"
1(

#340000
b100110 !
0"
1%
b100110 '
0(
1+
b100110 9

#345000
1"
1(
b1100110 ,
b100110 0
b100110 3
15
b1100110 6

#350000
0"
0%
0(
0+

#355000
1"
b1100110 &
1(
b1100110 -
b1100110 4
05

#360000
0"
0(

#365000
1"
1(

#370000
b10000000 !
0"
1#
b10000000 '
0(
1)
b10000000 7

#375000
1"
1(
b101010 ,
b10000000 .
b10000000 1
b101010 6

#380000
0"
0#
0(
0)

#385000
1"
1(

#390000
b10 !
0"
1$
b10 '
0(
1*
b10 8

#395000
1"
1(
b10000010 ,
b10 /
b10 2
b10000010 6

#400000
0"
0$
0(
0*

#405000
1"
1(

#410000
0"
1%
0(
1+
b10 9

#415000
1"
1(
b100000 ,
b10 0
b10 3
15
b100000 6

#420000
0"
0%
0(
0+

#425000
1"
b100000 &
1(
b100000 -
b100000 4
05

#430000
0"
0(

#435000
1"
1(

#440000
b10000000 !
0"
1#
b10000000 '
0(
1)

#445000
1"
1(

#450000
0"
0#
0(
0)

#455000
1"
1(

#460000
b101 !
0"
1$
b101 '
0(
1*
b101 8

#465000
1"
1(
b100 ,
b101 /
b101 2
b100 6

#470000
0"
0$
0(
0*

#475000
1"
1(

#480000
b11 !
0"
1%
b11 '
0(
1+
b11 9

#485000
1"
1(
b11111100 ,
b11 0
b11 3
15
b11111100 6

#490000
0"
0%
0(
0+

#495000
1"
b11111100 &
1(
b11111100 -
b11111100 4
05

#500000
0"
0(

#505000
1"
1(

#510000
b1111 !
0"
1#
b1111 '
0(
1)
b1111 7

#515000
1"
1(
b0 ,
b1111 .
b1111 1
b0 6

#520000
0"
0#
0(
0)

#525000
1"
1(

#530000
b11110000 !
0"
1$
b11110000 '
0(
1*
b11110000 8

#535000
1"
1(
b11110000 /
b11110000 2

#540000
0"
0$
0(
0*

#545000
1"
1(

#550000
b100111 !
0"
1%
b100111 '
0(
1+
b100111 9

#555000
1"
1(
b100111 0
b100111 3
15

#560000
0"
0%
0(
0+

#565000
1"
b0 &
1(
b0 -
b0 4
05

#570000
0"
0(

#575000
1"
1(

#580000
b11001000 !
0"
1#
b11001000 '
0(
1)
b11001000 7

#585000
1"
1(
b111 ,
b11001000 .
b11001000 1
b111 6

#590000
0"
0#
0(
0)

#595000
1"
1(

#600000
b1100100 !
0"
1$
b1100100 '
0(
1*
b1100100 8

#605000
1"
1(
b10011 ,
b1100100 /
b1100100 2
b10011 6

#610000
0"
0$
0(
0*

#615000
1"
1(

#620000
b100000 !
0"
1%
b100000 '
0(
1+
b100000 9

#625000
1"
1(
b101100 ,
b100000 0
b100000 3
15
b101100 6

#630000
0"
0%
0(
0+

#635000
1"
b101100 &
1(
b101100 -
b101100 4
05

#640000
0"
0(

#645000
1"
1(

#650000
b10100101 !
0"
1#
b10100101 '
0(
1)
b10100101 7

#655000
1"
1(
b1001 ,
b10100101 .
b10100101 1
b1001 6

#660000
0"
0#
0(
0)

#665000
1"
1(

#670000
b0 !
0"
1$
b0 '
0(
1*
b0 8

#675000
1"
1(
b10100101 ,
b0 /
b0 2
b10100101 6

#680000
0"
0$
0(
0*

#685000
1"
1(

#690000
b10 !
0"
1%
b10 '
0(
1+
b10 9

#695000
1"
1(
b10 0
b10 3
15

#700000
0"
0%
0(
0+

#705000
1"
b10100101 &
1(
b10100101 -
b10100101 4
05

#710000
0"
0(

#715000
1"
1(

#720000
b11111111 !
0"
1#
b11111111 '
0(
1)
b11111111 7

#725000
1"
1(
b11111111 ,
b11111111 .
b11111111 1
b11111111 6

#730000
0"
0#
0(
0)

#735000
1"
1(

#740000
b1010 !
0"
1$
b1010 '
0(
1*
b1010 8

#745000
1"
1(
b0 ,
b1010 /
b1010 2
b0 6

#750000
0"
0$
0(
0*

#755000
1"
1(

#760000
b10 !
0"
1%
b10 '
0(
1+

#765000
1"
1(
15

#770000
0"
0%
0(
0+

#775000
1"
b0 &
1(
b0 -
b0 4
05

#780000
0"
0(

#785000
1"
1(

#790000
b10100 !
0"
1#
b10100 '
0(
1)
b10100 7

#795000
1"
1(
b10100 .
b10100 1

#800000
0"
0#
0(
0)

#805000
1"
1(

#810000
0"
0(

#815000
1"
1(

#820000
b100000 !
0"
1%
b100000 '
0(
1+
b100000 9

#825000
1"
1(
b11110 ,
b100000 0
b100000 3
15
b11110 6

#830000
0"
0%
0(
0+

#835000
1"
b11110 &
1(
b11110 -
b11110 4
05

