TP1_ALU/TP1_ALU.srcs/sources_1/new/ALU_Core.v
`timescale 1ns / 1ps
//////////////////////////////////////////////////////////////////////////////////
// Company: UNC
// Engineer: 
// 
// Create Date: 08/27/2026 07:31:38 PM
// Design Name: 
// Module Name: ALU_Core
// Project Name:TP1-ALU 
// Target Devices: 
// Tool Versions: 
// Description: 
// 
// Dependencies: 
// 
// Revision:
// Revision 0.01 - File Created
// Additional Comments:
// 
//////////////////////////////////////////////////////////////////////////////////

module ALU_Core 
#(
    parameter NB_DATA = 8,
    parameter NB_OP   = 6 
)
(
    output wire [NB_DATA - 1 : 0] o_result,
    
    input wire [NB_DATA - 1 : 0] i_data_a, // dato A
    input wire [NB_DATA - 1 : 0] i_data_b, // dato B
    input wire [NB_OP   - 1 : 0] i_opcode  // Operacion
);
    
    localparam [NB_OP - 1 : 0] ADD = 6'b100000;
    localparam [NB_OP - 1 : 0] SUB = 6'b100010;
    localparam [NB_OP - 1 : 0] AND = 6'b100100;
    localparam [NB_OP - 1 : 0] OR  = 6'b100101;
    localparam [NB_OP - 1 : 0] XOR = 6'b100110;
    localparam [NB_OP - 1 : 0] SRA = 6'b000011;
    localparam [NB_OP - 1 : 0] SRL = 6'b000010;
    localparam [NB_OP - 1 : 0] NOR = 6'b100111;
  
    reg [NB_DATA - 1 : 0] res;
  
    always @(*)
    begin
        case(i_opcode)
            ADD : res = i_data_a + i_data_b;
            SUB : res = i_data_a - i_data_b;
            AND : res = i_data_a & i_data_b;
            OR  : res = i_data_a | i_data_b;
            XOR : res = i_data_a ^ i_data_b;
            SRA : res = i_data_a >>> i_data_b;
            SRL : res = i_data_a >> i_data_b;
            NOR : res = ~(i_data_a | i_data_b);
            default : res = {NB_DATA{1'b0}};
        endcase
    end
  
    assign o_result = res;
  
endmodule

TP1_ALU/TP1_ALU.srcs/sources_1/new/ALU_Top.v

`timescale 1ns / 1ps
//////////////////////////////////////////////////////////////////////////////////
// Company: UNC
// Engineer: 
// 
// Create Date: 08/27/2026 07:31:38 PM
// Design Name: 
// Module Name: ALU_Top
// Project Name:TP1-ALU 
// Target Devices: 
// Tool Versions: 
// Description: 
// 
// Dependencies: 
// 
// Revision:
// Revision 0.01 - File Created
// Additional Comments:
// 
//////////////////////////////////////////////////////////////////////////////////

module ALU_Top
#(
    parameter NB_DATA = 8,
    parameter NB_OP   = 6
)
(
    input  wire [NB_DATA - 1 : 0]      i_switches,
    input  wire                        i_load_1,     // Señal para cargar A
    input  wire                        i_load_2,     // Señal para cargar B
    input  wire                        i_load_3,     // Señal para cargar opcode y disparar resultado
    
    output wire [NB_DATA - 1 : 0]      o_leds
);

    // FF A
    reg [NB_DATA - 1 : 0] reg_a;
    
    always @(posedge i_load_1)
    begin
        reg_a <= i_switches;
    end

    // FF B
    reg [NB_DATA - 1 : 0] reg_b;
    always @(posedge i_load_2)
    begin
        reg_b <= i_switches;
    end

    // FF Opcode
    reg [NB_OP - 1 : 0] reg_opcode;
    always @(posedge i_load_3)
    begin
        reg_opcode <= i_switches[NB_OP - 1 : 0];
    end

    // Instancia del modulo ALU_Core
    wire [NB_DATA - 1 : 0] alu_result;

    ALU_Core #(
        .NB_DATA (NB_DATA),
        .NB_OP   (NB_OP)
    ) alu_core_inst (
        .o_result  (alu_result),
        .i_data_a  (reg_a),
        .i_data_b  (reg_b),
        .i_opcode  (reg_opcode)
    );

    // FF Salida
    reg [NB_DATA - 1 : 0] reg_result;
    always @(negedge i_load_3)
    begin
        reg_result <= alu_result;
    end

    assign o_leds = reg_result;

endmodule

TP1_ALU/TP1_ALU.srcs/sim_1/new/test_ALU_Top.v
`timescale 1ns / 1ps
//////////////////////////////////////////////////////////////////////////////////
// Company: UNC
// Engineer: 
// 
// Create Date: 08/27/2026 07:41:13 PM
// Design Name: 
// Module Name: test_ALU_Top
// Project Name: TP1_ALU
// Target Devices: 
// Tool Versions: 
// Description: 
// 
// Dependencies: 
// 
// Revision:
// Revision 0.01 - File Created
// Additional Comments:
// 
//////////////////////////////////////////////////////////////////////////////////

module test_ALU_Top;

    parameter NB_DATA = 8;
    parameter NB_OP   = 6;

    // Entradas
    reg  [NB_DATA - 1 : 0] i_switches;
    reg                    i_load_1;
    reg                    i_load_2;
    reg                    i_load_3;
    
    // Salida
    wire [NB_DATA - 1 : 0] o_leds;

    // DUT: Device Under Test
    ALU_Top #(
        .NB_DATA (NB_DATA),
        .NB_OP   (NB_OP)
    ) DUT (
        .i_switches (i_switches),
        .i_load_1   (i_load_1),
        .i_load_2   (i_load_2),
        .i_load_3   (i_load_3),
        .o_leds     (o_leds)
    );

    // Funciones reutilizables
    task load_a(input [NB_DATA - 1 : 0] value);
    begin
        i_switches = value;
        #10 i_load_1 = 1;
        #20 i_load_1 = 0;
        #10;
    end
    endtask

    task load_b(input [NB_DATA - 1 : 0] value);
    begin
        i_switches = value;
        #10 i_load_2 = 1;
        #20 i_load_2 = 0;
        #10;
    end
    endtask

    task load_opcode(input [NB_OP - 1 : 0] value);
    begin
        i_switches = value;
        #10 i_load_3 = 1;
        #20 i_load_3 = 0;   // negedge dispara reg_result aca
        #10;
    end
    endtask

    initial begin
        $dumpfile("dump.vcd");
        $dumpvars(0, test_ALU_Top);

        i_switches = 0;
        i_load_1   = 0;
        i_load_2   = 0;
        i_load_3   = 0;
        #20;

        // Caso 1: ADD, 5 + 3 = 8
        load_a(8'd5);
        load_b(8'd3);
        load_opcode(6'b100000);
        #10 $display("Caso 1  (ADD 5+3)        o_leds=%d  (esperado 8)", o_leds);

        // Caso 2: SUB, 10 - 4 = 6
        load_a(8'd10);
        load_b(8'd4);
        load_opcode(6'b100010);
        #10 $display("Caso 2  (SUB 10-4)       o_leds=%d  (esperado 6)", o_leds);

        // Caso 3: AND, 0xCC & 0xAA = 0x88
        load_a(8'hCC);
        load_b(8'hAA);
        load_opcode(6'b100100);
        #10 $display("Caso 3  (AND CC&AA)      o_leds=%h  (esperado 88)", o_leds);

        // Caso 4: OR, 0xCC | 0xAA = 0xEE
        load_a(8'hCC);
        load_b(8'hAA);
        load_opcode(6'b100101);
        #10 $display("Caso 4  (OR  CC|AA)      o_leds=%h  (esperado EE)", o_leds);

        // Caso 5: XOR, 0xCC ^ 0xAA = 0x66
        load_a(8'hCC);
        load_b(8'hAA);
        load_opcode(6'b100110);
        #10 $display("Caso 5  (XOR CC^AA)      o_leds=%h  (esperado 66)", o_leds);

        // Caso 6: SRL, 0x80 >> 2 = 0x20 (shift logico, rellena con 0)
        load_a(8'h80);
        load_b(8'd2);
        load_opcode(6'b000010);
        #10 $display("Caso 6  (SRL 80>>2)      o_leds=%h  (esperado 20)", o_leds);

        // Caso 7: SRA, 0x80 >>> 5 -> 8
        load_a(8'h80);
        load_b(8'd5);
        load_opcode(6'b000011);
        #10 $display("Caso 7  (SRA 80>>>5)     o_leds=%h (esperado 04)", o_leds);

        // Caso 8: NOR, 0x0F ~| 0xF0 = 0x00
        load_a(8'h0F);
        load_b(8'hF0);
        load_opcode(6'b100111);
        #10 $display("Caso 8  (NOR 0F,F0)      o_leds=%h  (esperado 00)", o_leds);

        // Caso 9: ADD con overflow, 200 + 100 = 300 -> 1 bit de Carry + 8 bits de salida (44d)
        load_a(8'd200);
        load_b(8'd100);
        load_opcode(6'b100000);
        #10 $display("Caso 9  (ADD overflow)   o_leds=%d  (esperado 44, 300 mod 256)", o_leds);

        // Caso 10: shift por 0 (no deberia cambiar nada)
        load_a(8'hA5);
        load_b(8'd0);
        load_opcode(6'b000010);   // SRL
        #10 $display("Caso 10 (SRL shift 0)    o_leds=%h  (esperado A5, sin cambios)", o_leds);

        // Caso 11: shift por un valor mayor al ancho de datos (8 bits)
        load_a(8'hFF);
        load_b(8'd10);            // desplazar 10 posiciones en un dato de 8 bits
        load_opcode(6'b000010);   // SRL
        #10 $display("Caso 11 (SRL shift >8)   o_leds=%h  (esperado 00, se vacia el registro)", o_leds);
        
        // Caso 12: cambiar solo el reg A0
        // no deberia cambiar la salida al no haber precionado el boton 3
        load_a(8'd20);
        #10 $display("Caso 12 (solo A cambio)  o_leds=%d  (esperado 0 TODAVIA, no se aprieto boton 3)", o_leds);

        // Caso 13: ahora si apretamos boton 3 de nuevo, sin cambiar opcode,
        // deberia recalcular con el A nuevo (20) y el B viejo (10) -> 30
        load_opcode(6'b100000); // ADD
        #10 $display("Caso 13 (dispara con A nuevo) o_leds=%d  (esperado 30)", o_leds);

        #50;
        $finish;
    end

endmodule

TP1_ALU/TP1_ALU.sim/sim_1/behav/xsim/dump.vcd
$date
   Fri Aug 28 10:42:01 2026
$end

$version
  2026.1
  $dumpfile ("dump.vcd") 
$end

$timescale
  1ps
$end

$scope module test_ALU_Top $end
$var reg 8 ! i_switches [7:0] $end
$var reg 1 " i_load_1 $end
$var reg 1 # i_load_2 $end
$var reg 1 $ i_load_3 $end
$var wire 8 % o_leds [7:0] $end
$scope module DUT $end
$var wire 8 & i_switches [7:0] $end
$var wire 1 ' i_load_1 $end
$var wire 1 ( i_load_2 $end
$var wire 1 ) i_load_3 $end
$var wire 8 % o_leds [7:0] $end
$var reg 8 * reg_a [7:0] $end
$var reg 8 + reg_b [7:0] $end
$var reg 6 , reg_opcode [5:0] $end
$var wire 8 - alu_result [7:0] $end
$var reg 8 . reg_result [7:0] $end
$scope module alu_core_inst $end
$var wire 8 - o_result [7:0] $end
$var wire 8 / i_data_a [7:0] $end
$var wire 8 0 i_data_b [7:0] $end
$var wire 6 1 i_opcode [5:0] $end
$var reg 8 2 res [7:0] $end
$upscope $end
$upscope $end
$scope task load_a $end
$var reg 8 3 value [7:0] $end
$upscope $end
$scope task load_b $end
$var reg 8 4 value [7:0] $end
$upscope $end
$scope task load_opcode $end
$var reg 6 5 value [5:0] $end
$upscope $end
$upscope $end
$enddefinitions $end

#0
$dumpvars
b0 !
0"
0#
0$
bx %
b0 &
0'
0(
0)
bx *
bx +
bx ,
bx -
bx .
bx /
bx 0
bx 1
bx 2
bx 3
bx 4
bx 5
$end

#20000
b101 !
b101 &
b101 3

#30000
1"
1'
b101 *
b0 -
b101 /
b0 2

#50000
0"
0'

#60000
b11 !
b11 &
b11 4

#70000
1#
1(
b11 +
b11 0

#90000
0#
0(

#100000
b100000 !
b100000 &
b100000 5

#110000
1$
1)
b100000 ,
b1000 -
b100000 1
b1000 2

#130000
0$
b1000 %
0)
b1000 .

#150000
b1010 !
b1010 &
b1010 3

#160000
1"
1'
b1010 *
b1101 -
b1010 /
b1101 2

#180000
0"
0'

#190000
b100 !
b100 &
b100 4

#200000
1#
1(
b100 +
b1110 -
b100 0
b1110 2

#220000
0#
0(

#230000
b100010 !
b100010 &
b100010 5

#240000
1$
1)
b100010 ,
b110 -
b100010 1
b110 2

#260000
0$
b110 %
0)
b110 .

#280000
b11001100 !
b11001100 &
b11001100 3

#290000
1"
1'
b11001100 *
b11001000 -
b11001100 /
b11001000 2

#310000
0"
0'

#320000
b10101010 !
b10101010 &
b10101010 4

#330000
1#
1(
b10101010 +
b100010 -
b10101010 0
b100010 2

#350000
0#
0(

#360000
b100100 !
b100100 &
b100100 5

#370000
1$
1)
b100100 ,
b10001000 -
b100100 1
b10001000 2

#390000
0$
b10001000 %
0)
b10001000 .

#410000
b11001100 !
b11001100 &

#420000
1"
1'

#440000
0"
0'

#450000
b10101010 !
b10101010 &

#460000
1#
1(

#480000
0#
0(

#490000
b100101 !
b100101 &
b100101 5

#500000
1$
1)
b100101 ,
b11101110 -
b100101 1
b11101110 2

#520000
0$
b11101110 %
0)
b11101110 .

#540000
b11001100 !
b11001100 &

#550000
1"
1'

#570000
0"
0'

#580000
b10101010 !
b10101010 &

#590000
1#
1(

#610000
0#
0(

#620000
b100110 !
b100110 &
b100110 5

#630000
1$
1)
b100110 ,
b1100110 -
b100110 1
b1100110 2

#650000
0$
b1100110 %
0)
b1100110 .

#670000
b10000000 !
b10000000 &
b10000000 3

#680000
1"
1'
b10000000 *
b101010 -
b10000000 /
b101010 2

#700000
0"
0'

#710000
b10 !
b10 &
b10 4

#720000
1#
1(
b10 +
b10000010 -
b10 0
b10000010 2

#740000
0#
0(

#750000
b10 5

#760000
1$
1)
b10 ,
b100000 -
b10 1
b100000 2

#780000
0$
b100000 %
0)
b100000 .

#800000
b10000000 !
b10000000 &

#810000
1"
1'

#830000
0"
0'

#840000
b101 !
b101 &
b101 4

#850000
1#
1(
b101 +
b100 -
b101 0
b100 2

#870000
0#
0(

#880000
b11 !
b11 &
b11 5

#890000
1$
1)
b11 ,
b11 1

#910000
0$
b100 %
0)
b100 .

#930000
b1111 !
b1111 &
b1111 3

#940000
1"
1'
b1111 *
b0 -
b1111 /
b0 2

#960000
0"
0'

#970000
b11110000 !
b11110000 &
b11110000 4

#980000
1#
1(
b11110000 +
b11110000 0

#1000000
0#
0(

#1010000
b100111 !
b100111 &
b100111 5

#1020000
1$
1)
b100111 ,
b100111 1

#1040000
0$
b0 %
0)
b0 .

#1060000
b11001000 !
b11001000 &
b11001000 3

#1070000
1"
1'
b11001000 *
b111 -
b11001000 /
b111 2

#1090000
0"
0'

#1100000
b1100100 !
b1100100 &
b1100100 4

#1110000
1#
1(
b1100100 +
b10011 -
b1100100 0
b10011 2

#1130000
0#
0(

#1140000
b100000 !
b100000 &
b100000 5

#1150000
1$
1)
b100000 ,
b101100 -
b100000 1
b101100 2

#1170000
0$
b101100 %
0)
b101100 .

#1190000
b10100101 !
b10100101 &
b10100101 3

#1200000
1"
1'
b10100101 *
b1001 -
b10100101 /
b1001 2

#1220000
0"
0'

#1230000
b0 !
b0 &
b0 4

#1240000
1#
1(
b0 +
b10100101 -
b0 0
b10100101 2

#1260000
0#
0(

#1270000
b10 !
b10 &
b10 5

#1280000
1$
1)
b10 ,
b10 1

#1300000
0$
b10100101 %
0)
b10100101 .

#1320000
b11111111 !
b11111111 &
b11111111 3

#1330000
1"
1'
b11111111 *
b11111111 -
b11111111 /
b11111111 2

#1350000
0"
0'

#1360000
b1010 !
b1010 &
b1010 4

#1370000
1#
1(
b1010 +
b0 -
b1010 0
b0 2

#1390000
0#
0(

#1400000
b10 !
b10 &

#1410000
1$
1)

#1430000
0$
b0 %
0)
b0 .

#1450000
b10100 !
b10100 &
b10100 3

#1460000
1"
1'
b10100 *
b10100 /

#1480000
0"
0'

#1500000
b100000 !
b100000 &
b100000 5

#1510000
1$
1)
b100000 ,
b11110 -
b100000 1
b11110 2

#1530000
0$
b11110 %
0)
b11110 .
